TIRAI/__init__.py
TIRAI/sdk/__init__.py
TIRAI/sdk/base.py
TIRAI/sdk/config.py
TIRAI/sdk/providers/__init__.py
TIRAI/sdk/providers/awsclaude.py
TIRAI/sdk/providers/azureopenai.py
TIRAI/sdk/providers/deepseek.py
TIRAI/sdk/providers/openai.py
TIRAI/sdk/providers/xai.py
TIRAI-0.2.1.dist-info/LICENSE
TIRAI-0.2.1.dist-info/METADATA
TIRAI-0.2.1.dist-info/WHEEL
TIRAI-0.2.1.dist-info/top_level.txt
TIRAI-0.2.1.dist-info/RECORD
