Metadata-Version: 2.2
Name: TIRAI
Version: 0.2.1
Summary: The I Research AI Tools
Home-page: https://github.com/TheIResearch/tirai-sdk
Author: The I Research
Author-email: jl@theiresearch.com
License: MIT License
Requires-Python: >=3.7
License-File: LICENSE
Requires-Dist: requests>=2.32.3
Dynamic: author
Dynamic: author-email
Dynamic: home-page
Dynamic: requires-python
